[{"room_id":4,"time_of_reservation":"03:20:13","category_id":3,"id":1,"available_seats":[true,true,true,true,true,true,true,true,true,true,true,true,true,true,true],"status":1},{"room_id":4,"time_of_reservation":"06:11:11","category_id":3,"id":2,"available_seats":[true,true,true,true,true,true,true,true,true,true,true,true,true,true,true],"status":2},{"room_id":4,"time_of_reservation":"05:25:13","category_id":1,"id":3,"available_seats":[true,true,true,true,true,true,true,true,true,true,true,true,true,true,true,true,true,true,true,true,true,true,true,true],"status":1},{"room_id":4,"time_of_reservation":"06:11:11","category_id":1,"id":4,"available_seats":[true,true,true,true,true,true,true,true,true,true,true,true,true,true,true,true,true,true,true,true,true,true,true,true],"status":2},{"room_id":4,"time_of_reservation":"05:50:13","category_id":2,"id":5,"available_seats":[true,true,true,true,true,true,true,true,true,true,true,true],"status":1},{"room_id":4,"time_of_reservation":"05:55:13","category_id":2,"id":6,"available_seats":[true,true,true,true,true,true,true,true,true,true,true,true],"status":1}]